examples/__init__.py
fitbit_downloader/__init__.py
fitbit_downloader/__main__.py
fitbit_downloader/authorize.py
fitbit_downloader/check_upload.py
fitbit_downloader/client.py
fitbit_downloader/config.py
fitbit_downloader/constants.py
fitbit_downloader/dateutils.py
fitbit_downloader/download.py
fitbit_downloader/download_samples.py
fitbit_downloader/ext_subprocess.py
fitbit_downloader/gather_keys_oauth2.py
fitbit_downloader/gen_models.py
fitbit_downloader/logger.py
fitbit_downloader/main.py
fitbit_downloader/models/__init__.py
fitbit_downloader/models/activityresponse.py
fitbit_downloader/models/distanceresponse.py
fitbit_downloader/models/elevationresponse.py
fitbit_downloader/models/floorsresponse.py
fitbit_downloader/models/heartresponse.py
fitbit_downloader/models/refreshtokenresponse.py
fitbit_downloader/models/sleepresponse.py
fitbit_downloader/models/stepsresponse.py
tests/__init__.py
tests/config.py
tests/conftest.py
tests/dirutils.py
tests/fake_client.py
tests/fixtures.py
tests/test_download.py
tests/test_models.py
tests/test_placeholder.py
fitbit_downloader-0.3.0.dist-info/LICENSE.md
fitbit_downloader-0.3.0.dist-info/METADATA
fitbit_downloader-0.3.0.dist-info/WHEEL
fitbit_downloader-0.3.0.dist-info/top_level.txt
fitbit_downloader-0.3.0.dist-info/RECORD
