Metadata-Version: 2.1
Name: fitbit-downloader
Version: 0.3.0
Summary: A CLI and Python tool for downloading Fitbit data
Home-page: https://github.com/nickderobertis/fitbit-downloader
Author: Nick DeRobertis
Author-email: whoopnip@gmail.com
License: MIT
Project-URL: Code, https://github.com/nickderobertis/fitbit-downloader
Project-URL: Documentation, https://nickderobertis.github.io/fitbit-downloader
Classifier: Development Status :: 3 - Alpha
Classifier: Intended Audience :: Developers
Classifier: Programming Language :: Python :: 3.6
Classifier: Programming Language :: Python :: 3.7
License-File: LICENSE.md
Requires-Dist: fitbit
Requires-Dist: cherrypy
Requires-Dist: pydantic[dotenv]
Requires-Dist: py-app-conf (>=0.4.1)
Requires-Dist: fs
